<?xml version="1.0" encoding="UTF-8"?>
<tv generator-info-name="Kan 11 Scraper">
  <channel id="Kan 11">
    <display-name>Kan 11</display-name>
  </channel>
  <programme start="20260324000000 +0000" stop="20260324003500 +0000" channel="Kan 11">
    <title lang="he">מבזק חדשות</title>
    <desc lang="he">מבזק חדשות</desc>
    <category lang="en">News</category>
    <episode-num system="original-air-date">2026-03-24</episode-num>
    <icon src="https://raw.githubusercontent.com/EMPmaster/tv-guide/main/images/kan/landscape/184e38e122683ba5a34b1e1793f3bc28.jpg" />
  </programme>
  <programme start="20260324003500 +0000" stop="20260324010000 +0000" channel="Kan 11">
    <title lang="he">סיפורים מהכורסה</title>
    <sub-title lang="he">3 - חופשות</sub-title>
    <desc lang="he">האנשים הכי מצחיקים מספרים את הסיפור של כולנו. והפעם, סיפורי חופשות: מה חיכה לאוראל צברי במיטה בירח הדבש במלדיביים? מה אושרית סרוסי עשתה ביורודיסני עם קופסת שימורים? ואיפה מבלה ציפי שביט את החופש הגדול?</desc>
    <category lang="en">Series</category>
    <episode-num system="original-air-date">2026-03-24</episode-num>
    <icon src="https://raw.githubusercontent.com/EMPmaster/tv-guide/main/images/kan/landscape/d3cc4f56355c558b3a3dc8e5b01a9a3c.jpg" />
  </programme>
  <programme start="20260324010000 +0000" stop="20260324011500 +0000" channel="Kan 11">
    <title lang="he">מבזק חדשות</title>
    <desc lang="he">מבזק חדשות</desc>
    <category lang="en">News</category>
    <episode-num system="original-air-date">2026-03-24</episode-num>
    <icon src="https://raw.githubusercontent.com/EMPmaster/tv-guide/main/images/kan/landscape/184e38e122683ba5a34b1e1793f3bc28.jpg" />
  </programme>
  <programme start="20260324011500 +0000" stop="20260324020000 +0000" channel="Kan 11">
    <title lang="he">שלומי שבן מארח</title>
    <sub-title lang="he">יסמין מועלם</sub-title>
    <desc lang="he">יסמין מספרת לשלומי איך זה להוציא אלבום ולהצליח בזמן קורונה, ולפגוש את הקהל שלה רק דרך מסך! האורחת המיוחדת שלה היא לא אחרת מלאה שבת , הן מבצעות ביחד עם שלומי שיר של לאה בעיבוד מחודש ומיוחד לתוכנית.</desc>
    <category lang="en">Series</category>
    <episode-num system="original-air-date">2026-03-24</episode-num>
    <icon src="https://raw.githubusercontent.com/EMPmaster/tv-guide/main/images/kan/landscape/656d06f77b98393afc1f2bcb948393cc.jpg" />
  </programme>
  <programme start="20260324020000 +0000" stop="20260324020500 +0000" channel="Kan 11">
    <title lang="he">מבזק חדשות</title>
    <desc lang="he">מבזק חדשות</desc>
    <category lang="en">News</category>
    <episode-num system="original-air-date">2026-03-24</episode-num>
    <icon src="https://raw.githubusercontent.com/EMPmaster/tv-guide/main/images/kan/landscape/184e38e122683ba5a34b1e1793f3bc28.jpg" />
  </programme>
  <programme start="20260324020500 +0000" stop="20260324023600 +0000" channel="Kan 11">
    <title lang="he">אומרים שהיה פה</title>
    <sub-title lang="he">5</sub-title>
    <desc lang="he">ישראל בקושי בת שבע וכבר מתמודדת עם שערוריות של גדולים: משפט הדיבה שהגיע עד לשטן, הפתק הקטן שהסעיר מדינה שלמה והטרמפ של יהונתן גפן שהצליח להרגיז את המשורר דוד אבידן.</desc>
    <category lang="en">Series</category>
    <episode-num system="onscreen">S1954E5</episode-num>
    <icon src="https://raw.githubusercontent.com/EMPmaster/tv-guide/main/images/kan/landscape/5f4ded6352ee91b840ba8a7370259a12.jpg" />
  </programme>
  <programme start="20260324023600 +0000" stop="20260324030000 +0000" channel="Kan 11">
    <title lang="he">הבלתי חשובים</title>
    <sub-title lang="he">ילדי ה׳ באייר</sub-title>
    <desc lang="he">ההיסטוריה שלנו מלאה באירועים שבמבט ראשון  נראים בלתי חשובים, אך ממרחק השנים, מספרים סיפור גדול יותר על מי שהיינו ומה שאנחנו היום. הפרק מספר על ילדי ה&apos; באייר תש&quot;ח, שנולדו ממש עם מדינת ישראל.</desc>
    <category lang="en">Series</category>
    <episode-num system="original-air-date">2026-03-24</episode-num>
    <icon src="https://raw.githubusercontent.com/EMPmaster/tv-guide/main/images/kan/landscape/061447c05e36d16c82ceed7bd90bcdf2.jpg" />
  </programme>
  <programme start="20260324030000 +0000" stop="20260324031500 +0000" channel="Kan 11">
    <title lang="he">מבזק חדשות</title>
    <desc lang="he">מבזק חדשות</desc>
    <category lang="en">News</category>
    <episode-num system="original-air-date">2026-03-24</episode-num>
    <icon src="https://raw.githubusercontent.com/EMPmaster/tv-guide/main/images/kan/landscape/184e38e122683ba5a34b1e1793f3bc28.jpg" />
  </programme>
  <programme start="20260324031500 +0000" stop="20260324034500 +0000" channel="Kan 11">
    <title lang="he">שיר אחד</title>
    <sub-title lang="he">שיר לערב חג</sub-title>
    <desc lang="he">סיפורו של השיר &quot;שיר לערב חג&quot;, שיר אהבה שכתבה תרצה אתר לאביה נתן אלתרמן, ומירי אלוני הפכה אותו ללהיט בפסטיבל הזמר והפזמון ב - 1973. אבל מאחורי הלחן מסתתר גלגול נוסף ונשכח של מילים אחרות שנגנזו.</desc>
    <category lang="en">Series</category>
    <episode-num system="original-air-date">2026-03-24</episode-num>
    <icon src="https://raw.githubusercontent.com/EMPmaster/tv-guide/main/images/kan/landscape/143619d6989cb01b29e0c06005cb0f7e.jpg" />
  </programme>
  <programme start="20260324034500 +0000" stop="20260324040000 +0000" channel="Kan 11">
    <title lang="he">מהצד השני עם גיא זהר</title>
    <desc lang="he">בימים של שטף בלתי פוסק של מסרים ואינפורמציה, יש מי שמנסה לעשות סדר. גיא זהר בטור יומי, חושף את הפער שבין המציאות לבין הדרך בה היא משתקפת בתקשורת, ואת המנגנונים שמעצבים לנו אותה.</desc>
    <category lang="en">Series</category>
    <episode-num system="original-air-date">2026-03-24</episode-num>
    <icon src="https://raw.githubusercontent.com/EMPmaster/tv-guide/main/images/kan/landscape/7fc074205e6ec57ae2af029c902e3c2b.jpg" />
  </programme>
  <programme start="20260324040000 +0000" stop="20260324060000 +0000" channel="Kan 11">
    <title lang="he">הבוקר הזה עם יאיר ויינרב</title>
    <desc lang="he">שידור חי של יומן הבוקר מ&quot;כאן חדשות ברשת ב&quot;.</desc>
    <category lang="en">News</category>
    <episode-num system="original-air-date">2026-03-24</episode-num>
    <icon src="https://raw.githubusercontent.com/EMPmaster/tv-guide/main/images/kan/landscape/99b149eb4ccc2013d1076f650b0e5b05.jpg" />
  </programme>
  <programme start="20260324060000 +0000" stop="20260324080000 +0000" channel="Kan 11">
    <title lang="he">קלמן ליברמן</title>
    <desc lang="he">שידור חי של תוכנית הרדיו של &quot;כאן חדשות ברשת ב&quot;.</desc>
    <category lang="en">Series</category>
    <episode-num system="original-air-date">2026-03-24</episode-num>
    <icon src="https://raw.githubusercontent.com/EMPmaster/tv-guide/main/images/kan/landscape/62cfa894e789926f7e62a22be1cfb796.jpg" />
  </programme>
  <programme start="20260324080000 +0000" stop="20260324100000 +0000" channel="Kan 11">
    <title lang="he">סדר יום עם קרן נויבך</title>
    <desc lang="he">שידור חי מאולפני &quot;כאן חדשות ברשת ב&quot; של תוכנית האקטואליה היומית.</desc>
    <category lang="en">Series</category>
    <episode-num system="original-air-date">2026-03-24</episode-num>
    <icon src="https://raw.githubusercontent.com/EMPmaster/tv-guide/main/images/kan/landscape/d45d91e3d417f9e0d7f8781c92e2a347.jpg" />
  </programme>
  <programme start="20260324100000 +0000" stop="20260324120000 +0000" channel="Kan 11">
    <title lang="he">משדר מיוחד עם שרון ואורי</title>
    <desc lang="he">משדר חדשות מיוחד עם שרון וכסלר ואורי לוי.</desc>
    <category lang="en">News</category>
    <episode-num system="original-air-date">2026-03-24</episode-num>
    <icon src="https://raw.githubusercontent.com/EMPmaster/tv-guide/main/images/kan/landscape/f99e66797e4dd9ed3781a31790152397.jpg" />
  </programme>
  <programme start="20260324120000 +0000" stop="20260324140000 +0000" channel="Kan 11">
    <title lang="he">משדר מיוחד עם יונתן אוחיון</title>
    <desc lang="he">משדר חדשות מיוחד עם יונתן אוחיון.</desc>
    <category lang="en">News</category>
    <episode-num system="original-air-date">2026-03-24</episode-num>
    <icon src="https://raw.githubusercontent.com/EMPmaster/tv-guide/main/images/kan/landscape/f99e66797e4dd9ed3781a31790152397.jpg" />
  </programme>
  <programme start="20260324140000 +0000" stop="20260324160000 +0000" channel="Kan 11">
    <title lang="he">משדר מיוחד עם מאיה ראכלין</title>
    <desc lang="he">משדר חדשות מיוחד עם מאיה ראכלין.</desc>
    <category lang="en">News</category>
    <episode-num system="original-air-date">2026-03-24</episode-num>
    <icon src="https://raw.githubusercontent.com/EMPmaster/tv-guide/main/images/kan/landscape/f99e66797e4dd9ed3781a31790152397.jpg" />
  </programme>
  <programme start="20260324160000 +0000" stop="20260324175000 +0000" channel="Kan 11">
    <title lang="he">משדר מיוחד עם איילה חסון</title>
    <desc lang="he">משדר חדשות מיוחד עם איילה חסון.</desc>
    <category lang="en">News</category>
    <episode-num system="original-air-date">2026-03-24</episode-num>
    <icon src="https://raw.githubusercontent.com/EMPmaster/tv-guide/main/images/kan/landscape/f99e66797e4dd9ed3781a31790152397.jpg" />
  </programme>
  <programme start="20260324175000 +0000" stop="20260324193000 +0000" channel="Kan 11">
    <title lang="he">מהדורת כאן חדשות עם טל ברמן</title>
    <desc lang="he">מהדורת החדשות המרכזית של כאן 11 עם נבחרת הכתבים והפרשנים של כאן חדשות. הפרסומים הראשונים, הכותרות החמות וכל הפרשנויות לצד כתבות מגזין ופינות קבועות.</desc>
    <category lang="en">News</category>
    <episode-num system="original-air-date">2026-03-24</episode-num>
    <icon src="https://raw.githubusercontent.com/EMPmaster/tv-guide/main/images/kan/landscape/7a04ba8f5e74f1d0dbcb0373d86cf287.jpg" />
  </programme>
  <programme start="20260324193000 +0000" stop="20260324201000 +0000" channel="Kan 11">
    <title lang="he">זהו זה!</title>
    <desc lang="he">החמישייה המופלאה - מוני מושונוב, גידי גוב, דבל&apos;ה גליקמן, אבי קושניר ושלמה בראבא - ממשיכה להצחיק ולרגש במערכונים מרעננים ושירים אהובים. הפעם הם יארחו את נינט לשיר משותף.</desc>
    <category lang="en">Series</category>
    <episode-num system="original-air-date">2026-03-24</episode-num>
    <icon src="https://raw.githubusercontent.com/EMPmaster/tv-guide/main/images/kan/landscape/1718b189e10c5d29d854551bbbef2346.jpg" />
  </programme>
  <programme start="20260324201000 +0000" stop="20260324205200 +0000" channel="Kan 11">
    <title lang="he">הורים בטיפול</title>
    <sub-title lang="he">פרק 5</sub-title>
    <desc lang="he">בפרק החמישי: איך מתמודדים עם ריחוק בין אב לבן, מה הקשר בין זוגיות להורות, ומה עושים כשיש פערים בגישות חינוכיות בין ההורים? הפסיכולוגים מספקים כלים לשימור הזוגיות ולחיזוק הקשר הבין-דורי במשפחה.</desc>
    <category lang="en">Series</category>
    <episode-num system="onscreen">S1E5</episode-num>
    <icon src="https://raw.githubusercontent.com/EMPmaster/tv-guide/main/images/kan/landscape/16f32bdbc27dbe4306f469f75f172951.jpg" />
  </programme>
  <programme start="20260324205200 +0000" stop="20260324220000 +0000" channel="Kan 11">
    <title lang="he">חדשות הלילה עם שרון דוידוביץ&apos;</title>
    <desc lang="he">רגע לפני שהיום נגמר, חדשות הלילה תסכם עבורכם את כל הדברים החשובים והמעניינים שקרו היום – מזווית קצת אחרת.</desc>
    <category lang="en">News</category>
    <episode-num system="original-air-date">2026-03-24</episode-num>
    <icon src="https://raw.githubusercontent.com/EMPmaster/tv-guide/main/images/kan/landscape/4cb0dc1cda860f43b6be7da0eb09fcef.jpg" />
  </programme>
  <programme start="20260324220000 +0000" stop="20260324221500 +0000" channel="Kan 11">
    <title lang="he">מהצד השני עם גיא זהר</title>
    <desc lang="he">בימים של שטף בלתי פוסק של מסרים ואינפורמציה, יש מי שמנסה לעשות סדר. גיא זהר בטור יומי, חושף את הפער שבין המציאות לבין הדרך בה היא משתקפת בתקשורת, ואת המנגנונים שמעצבים לנו אותה.</desc>
    <category lang="en">Series</category>
    <episode-num system="original-air-date">2026-03-24</episode-num>
    <icon src="https://raw.githubusercontent.com/EMPmaster/tv-guide/main/images/kan/landscape/7fc074205e6ec57ae2af029c902e3c2b.jpg" />
  </programme>
  <programme start="20260324221500 +0000" stop="20260324230000 +0000" channel="Kan 11">
    <title lang="he">הסוכנות</title>
    <sub-title lang="he">פרק 9-עקבות</sub-title>
    <desc lang="he">עונה שלישית לסדרת המתח הצרפתית. פרק 9: דיה ואנשי הסוכנות עושים הכול כדי לאתר את מלוטרו, שהצליח לטשטש את עקבותיו במומחיות. מצבה של מרינה בבאקו מסתבך כאשר פיליפ מתחיל לחשוד שזו לא המשימה הראשונה שלה.</desc>
    <category lang="en">Series</category>
    <episode-num system="onscreen">S3E9</episode-num>
    <icon src="https://raw.githubusercontent.com/EMPmaster/tv-guide/main/images/kan/landscape/69e984529180222f94f358eea9b3533b.jpg" />
  </programme>
  <programme start="20260324230000 +0000" stop="20260324231700 +0000" channel="Kan 11">
    <title lang="he">מבזק חדשות</title>
    <desc lang="he">מבזק חדשות</desc>
    <category lang="en">News</category>
    <episode-num system="original-air-date">2026-03-24</episode-num>
    <icon src="https://raw.githubusercontent.com/EMPmaster/tv-guide/main/images/kan/landscape/184e38e122683ba5a34b1e1793f3bc28.jpg" />
  </programme>
  <programme start="20260324231700 +0000" stop="20260324234600 +0000" channel="Kan 11">
    <title lang="he">מועדון הסטנד אפ</title>
    <sub-title lang="he">8</sub-title>
    <desc lang="he">תכנית בידור שבה קטעי סטנד אפ קמים לתחייה והופכים למערכונים. הפעם: נלי תגר מתגעגעת לאוכל של אמא, איתי זבולון מתכונן לעתיד, אלי חביב שר בציבור, גורי אלפי מנסה לישון עד מאוחר, ותום יער על רומנטיקה ופלוצים.</desc>
    <category lang="en">Series</category>
    <episode-num system="onscreen">S1E8</episode-num>
    <icon src="https://raw.githubusercontent.com/EMPmaster/tv-guide/main/images/kan/landscape/1179f0c175233b23de59bd5ada40998f.jpg" />
  </programme>
  <programme start="20260324234600 +0000" stop="20260325000000 +0000" channel="Kan 11">
    <title lang="he">סבתא בישלה עם תום יער</title>
    <sub-title lang="he">ידיים עובדות</sub-title>
    <desc lang="he">תום יער במסע קולינרי בין דורי. הפעם היא פוגשת את סבתא פיורלה האיטלקיה וסבתא אתרי הגרוזינית, שמכינות הכל בידיים. תום תתפייס עם צ׳ורצ׳חלה ותנסה לקלף ארטישוק לשביעות רצון הסבתא הכי קשוחה שפגשה אי פעם.</desc>
    <category lang="en">Series</category>
    <episode-num system="original-air-date">2026-03-24</episode-num>
    <icon src="https://raw.githubusercontent.com/EMPmaster/tv-guide/main/images/kan/landscape/cb8e91ba1988a29164b17d5ad6b25c78.jpg" />
  </programme>
  <programme start="20260325000000 +0000" stop="20260325003800 +0000" channel="Kan 11">
    <title lang="he">מבזק חדשות</title>
    <desc lang="he">מבזק חדשות</desc>
    <category lang="en">News</category>
    <episode-num system="original-air-date">2026-03-25</episode-num>
    <icon src="https://raw.githubusercontent.com/EMPmaster/tv-guide/main/images/kan/landscape/184e38e122683ba5a34b1e1793f3bc28.jpg" />
  </programme>
  <programme start="20260325003800 +0000" stop="20260325010000 +0000" channel="Kan 11">
    <title lang="he">סיפורים מהכורסה</title>
    <sub-title lang="he">העיר שלי</sub-title>
    <desc lang="he">האנשים הכי מצחיקים מספרים את הסיפור של כולנו. והפעם, העיר שלי: למה התחנה המרכזית בבאר שבע משפרת מצב רוח לנשים רווקות? על מי בולשות שכנות זקנות בכפר סבא בלילה? ואיך שוכרים דירה בתל אביב, בלי לראות אותה?</desc>
    <category lang="en">Series</category>
    <episode-num system="original-air-date">2026-03-25</episode-num>
    <icon src="https://raw.githubusercontent.com/EMPmaster/tv-guide/main/images/kan/landscape/d3cc4f56355c558b3a3dc8e5b01a9a3c.jpg" />
  </programme>
  <programme start="20260325010000 +0000" stop="20260325012300 +0000" channel="Kan 11">
    <title lang="he">מבזק חדשות</title>
    <desc lang="he">מבזק חדשות</desc>
    <category lang="en">News</category>
    <episode-num system="original-air-date">2026-03-25</episode-num>
    <icon src="https://raw.githubusercontent.com/EMPmaster/tv-guide/main/images/kan/landscape/184e38e122683ba5a34b1e1793f3bc28.jpg" />
  </programme>
  <programme start="20260325012300 +0000" stop="20260325020000 +0000" channel="Kan 11">
    <title lang="he">שלומי שבן מארח</title>
    <sub-title lang="he">שלומי שבת</sub-title>
    <desc lang="he">שלומי שבן מארח בהיכל התרבות את שלומי שבת. שבן מלווה את שבת בשירה, בפסנתר ובגיטרה. הם משוחחים על מוזיקה ועל החיים, וכמובן גם על ה&quot;פיל שבחדר&quot;-השם הכמעט זהה שלהם, ועל שלל תקריות מצחיקות ומביכות שעברו בגללו.</desc>
    <category lang="en">Series</category>
    <episode-num system="original-air-date">2026-03-25</episode-num>
    <icon src="https://raw.githubusercontent.com/EMPmaster/tv-guide/main/images/kan/landscape/656d06f77b98393afc1f2bcb948393cc.jpg" />
  </programme>
  <programme start="20260325020000 +0000" stop="20260325020500 +0000" channel="Kan 11">
    <title lang="he">מבזק חדשות</title>
    <desc lang="he">מבזק חדשות</desc>
    <category lang="en">News</category>
    <episode-num system="original-air-date">2026-03-25</episode-num>
    <icon src="https://raw.githubusercontent.com/EMPmaster/tv-guide/main/images/kan/landscape/184e38e122683ba5a34b1e1793f3bc28.jpg" />
  </programme>
  <programme start="20260325020500 +0000" stop="20260325023900 +0000" channel="Kan 11">
    <title lang="he">אומרים שהיה פה</title>
    <sub-title lang="he">7</sub-title>
    <desc lang="he">איך יצאנו למבצע קדש אבל הסתבכנו בדרך במקום מרוחק מאוד מהר סיני?  מיהו השחקן ההוליוודי המפורסם שהסתכסך עם אבא של יהונתן גפן וסיפורה של תוכנית הרדיו שהצחיקה את העם אבל הרגיזה את הממשלה.</desc>
    <category lang="en">Series</category>
    <episode-num system="onscreen">S1956E7</episode-num>
    <icon src="https://raw.githubusercontent.com/EMPmaster/tv-guide/main/images/kan/landscape/5f4ded6352ee91b840ba8a7370259a12.jpg" />
  </programme>
  <programme start="20260325023900 +0000" stop="20260325030000 +0000" channel="Kan 11">
    <title lang="he">הבלתי חשובים</title>
    <sub-title lang="he">קלפים פתוחים</sub-title>
    <desc lang="he">סדרה היסטורית על אירועים שנראים בלתי חשובים, אך ממרחק השנים מספרים סיפור גדול יותר על כולנו. והפעם: סיפור המאבק לשידור התוכנית &quot;קלפים פתוחים&quot;-למה שר החינוך רצה לצנזר אותה ומה קרה כשזה הגיע לבג&quot;ץ?</desc>
    <category lang="en">Series</category>
    <episode-num system="original-air-date">2026-03-25</episode-num>
    <icon src="https://raw.githubusercontent.com/EMPmaster/tv-guide/main/images/kan/landscape/061447c05e36d16c82ceed7bd90bcdf2.jpg" />
  </programme>
  <programme start="20260325030000 +0000" stop="20260325031500 +0000" channel="Kan 11">
    <title lang="he">מבזק חדשות</title>
    <desc lang="he">מבזק חדשות</desc>
    <category lang="en">News</category>
    <episode-num system="original-air-date">2026-03-25</episode-num>
    <icon src="https://raw.githubusercontent.com/EMPmaster/tv-guide/main/images/kan/landscape/184e38e122683ba5a34b1e1793f3bc28.jpg" />
  </programme>
  <programme start="20260325031500 +0000" stop="20260325034500 +0000" channel="Kan 11">
    <title lang="he">שיר אחד</title>
    <sub-title lang="he">לכל אחד יש</sub-title>
    <desc lang="he">סיפורו של השיר &quot;לכל אחד יש&quot; - השיר שהביא את המוזיקה הים תיכונית למרכז הבמה וגם את היוצרים שמאחוריו. שלומי שבת, ליאור נרקיס ועוזי חיטמן מצאו אחד את השני ברגע משמעותי בקריירה של כל אחד מהם, והצליחו לשתף פעולה.</desc>
    <category lang="en">Series</category>
    <episode-num system="original-air-date">2026-03-25</episode-num>
    <icon src="https://raw.githubusercontent.com/EMPmaster/tv-guide/main/images/kan/landscape/143619d6989cb01b29e0c06005cb0f7e.jpg" />
  </programme>
  <programme start="20260325034500 +0000" stop="20260325040000 +0000" channel="Kan 11">
    <title lang="he">מהצד השני עם גיא זהר</title>
    <desc lang="he">בימים של שטף בלתי פוסק של מסרים ואינפורמציה, יש מי שמנסה לעשות סדר. גיא זהר בטור יומי, חושף את הפער שבין המציאות לבין הדרך בה היא משתקפת בתקשורת, ואת המנגנונים שמעצבים לנו אותה.</desc>
    <category lang="en">Series</category>
    <episode-num system="original-air-date">2026-03-25</episode-num>
    <icon src="https://raw.githubusercontent.com/EMPmaster/tv-guide/main/images/kan/landscape/7fc074205e6ec57ae2af029c902e3c2b.jpg" />
  </programme>
  <programme start="20260325040000 +0000" stop="20260325060000 +0000" channel="Kan 11">
    <title lang="he">הבוקר הזה עם אריה גולן</title>
    <desc lang="he">שידור חי של יומן הבוקר מ&quot;כאן חדשות ברשת ב&quot;.</desc>
    <category lang="en">News</category>
    <episode-num system="original-air-date">2026-03-25</episode-num>
    <icon src="https://raw.githubusercontent.com/EMPmaster/tv-guide/main/images/kan/landscape/99b149eb4ccc2013d1076f650b0e5b05.jpg" />
  </programme>
  <programme start="20260325060000 +0000" stop="20260325080000 +0000" channel="Kan 11">
    <title lang="he">קלמן ליברמן</title>
    <desc lang="he">שידור חי של תוכנית הרדיו של &quot;כאן חדשות ברשת ב&quot;.</desc>
    <category lang="en">Series</category>
    <episode-num system="original-air-date">2026-03-25</episode-num>
    <icon src="https://raw.githubusercontent.com/EMPmaster/tv-guide/main/images/kan/landscape/62cfa894e789926f7e62a22be1cfb796.jpg" />
  </programme>
  <programme start="20260325080000 +0000" stop="20260325100000 +0000" channel="Kan 11">
    <title lang="he">סדר יום עם קרן נויבך</title>
    <desc lang="he">שידור חי מאולפני &quot;כאן חדשות ברשת ב&quot; של תוכנית האקטואליה היומית.</desc>
    <category lang="en">Series</category>
    <episode-num system="original-air-date">2026-03-25</episode-num>
    <icon src="https://raw.githubusercontent.com/EMPmaster/tv-guide/main/images/kan/landscape/d45d91e3d417f9e0d7f8781c92e2a347.jpg" />
  </programme>
  <programme start="20260325100000 +0000" stop="20260325120000 +0000" channel="Kan 11">
    <title lang="he">משדר מיוחד עם שרון ואורי</title>
    <desc lang="he">משדר חדשות מיוחד עם שרון וכסלר ואורי לוי.</desc>
    <category lang="en">News</category>
    <episode-num system="original-air-date">2026-03-25</episode-num>
    <icon src="https://raw.githubusercontent.com/EMPmaster/tv-guide/main/images/kan/landscape/f99e66797e4dd9ed3781a31790152397.jpg" />
  </programme>
  <programme start="20260325120000 +0000" stop="20260325140000 +0000" channel="Kan 11">
    <title lang="he">משדר מיוחד עם יונתן אוחיון</title>
    <desc lang="he">משדר חדשות מיוחד עם יונתן אוחיון.</desc>
    <category lang="en">News</category>
    <episode-num system="original-air-date">2026-03-25</episode-num>
    <icon src="https://raw.githubusercontent.com/EMPmaster/tv-guide/main/images/kan/landscape/f99e66797e4dd9ed3781a31790152397.jpg" />
  </programme>
  <programme start="20260325140000 +0000" stop="20260325160000 +0000" channel="Kan 11">
    <title lang="he">משדר מיוחד עם מאיה ראכלין</title>
    <desc lang="he">משדר חדשות מיוחד עם מאיה ראכלין.</desc>
    <category lang="en">News</category>
    <episode-num system="original-air-date">2026-03-25</episode-num>
    <icon src="https://raw.githubusercontent.com/EMPmaster/tv-guide/main/images/kan/landscape/f99e66797e4dd9ed3781a31790152397.jpg" />
  </programme>
  <programme start="20260325160000 +0000" stop="20260325175000 +0000" channel="Kan 11">
    <title lang="he">משדר מיוחד עם איילה חסון</title>
    <desc lang="he">משדר חדשות מיוחד עם איילה חסון.</desc>
    <category lang="en">News</category>
    <episode-num system="original-air-date">2026-03-25</episode-num>
    <icon src="https://raw.githubusercontent.com/EMPmaster/tv-guide/main/images/kan/landscape/f99e66797e4dd9ed3781a31790152397.jpg" />
  </programme>
  <programme start="20260325175000 +0000" stop="20260325193000 +0000" channel="Kan 11">
    <title lang="he">מהדורת כאן חדשות עם טלי מורנו</title>
    <desc lang="he">מהדורת החדשות המרכזית של כאן 11 עם נבחרת הכתבים והפרשנים של כאן חדשות. הפרסומים הראשונים, הכותרות החמות וכל הפרשנויות לצד כתבות מגזין ופינות קבועות.</desc>
    <category lang="en">News</category>
    <episode-num system="original-air-date">2026-03-25</episode-num>
    <icon src="https://raw.githubusercontent.com/EMPmaster/tv-guide/main/images/kan/landscape/7a04ba8f5e74f1d0dbcb0373d86cf287.jpg" />
  </programme>
  <programme start="20260325193000 +0000" stop="20260325201000 +0000" channel="Kan 11">
    <title lang="he">פגישה עם רוני קובן</title>
    <sub-title lang="he">רותי ברודו</sub-title>
    <desc lang="he">רותי ברודו, כוכבת תוכניות הבישול, בעלת מסעדות בתי קפה ובתי מלון, מספרת על ההתמודדות עם המראה שלה, על הקשיחות, על הילדות בצל השואה, על חיבתה לקבל ולתת ביקורת, ואיך נפרדה סופית מהאפשרות להיות אמא.</desc>
    <category lang="en">Series</category>
    <episode-num system="original-air-date">2026-03-25</episode-num>
    <icon src="https://raw.githubusercontent.com/EMPmaster/tv-guide/main/images/kan/landscape/e57798059334ff7398ab148d8c13d77a.jpg" />
  </programme>
  <programme start="20260325201000 +0000" stop="20260325220000 +0000" channel="Kan 11">
    <title lang="he">חדשות הלילה עם שרון דוידוביץ&apos;</title>
    <desc lang="he">רגע לפני שהיום נגמר, חדשות הלילה תסכם עבורכם את כל הדברים החשובים והמעניינים שקרו היום – מזווית קצת אחרת.</desc>
    <category lang="en">News</category>
    <episode-num system="original-air-date">2026-03-25</episode-num>
    <icon src="https://raw.githubusercontent.com/EMPmaster/tv-guide/main/images/kan/landscape/4cb0dc1cda860f43b6be7da0eb09fcef.jpg" />
  </programme>
  <programme start="20260325220000 +0000" stop="20260325221500 +0000" channel="Kan 11">
    <title lang="he">מהצד השני עם גיא זהר</title>
    <desc lang="he">בימים של שטף בלתי פוסק של מסרים ואינפורמציה, יש מי שמנסה לעשות סדר. גיא זהר בטור יומי, חושף את הפער שבין המציאות לבין הדרך בה היא משתקפת בתקשורת, ואת המנגנונים שמעצבים לנו אותה.</desc>
    <category lang="en">Series</category>
    <episode-num system="original-air-date">2026-03-25</episode-num>
    <icon src="https://raw.githubusercontent.com/EMPmaster/tv-guide/main/images/kan/landscape/7fc074205e6ec57ae2af029c902e3c2b.jpg" />
  </programme>
  <programme start="20260325221500 +0000" stop="20260325231800 +0000" channel="Kan 11">
    <title lang="he">הסוכנות</title>
    <sub-title lang="he">פרק אחרון לעונה</sub-title>
    <desc lang="he">פרק אחרון לעונה - הזדמנות חד - פעמית: פיליפ ממשיך לכלוא את מרינה בבית המלון בזמן שאנשי המוסד מתכננים לחסל אותה. מארי-ז&apos;אן מגלה על פגישה סודית בין נדיה למלוטרו ומחליטה לנצל את ההזדמנות כדי לתפוס אותו.</desc>
    <category lang="en">Series</category>
    <episode-num system="original-air-date">2026-03-25</episode-num>
    <icon src="https://raw.githubusercontent.com/EMPmaster/tv-guide/main/images/kan/landscape/69e984529180222f94f358eea9b3533b.jpg" />
  </programme>
  <programme start="20260325231800 +0000" stop="20260325232300 +0000" channel="Kan 11">
    <title lang="he">מבזק חדשות</title>
    <desc lang="he">מבזק חדשות</desc>
    <category lang="en">News</category>
    <episode-num system="original-air-date">2026-03-25</episode-num>
    <icon src="https://raw.githubusercontent.com/EMPmaster/tv-guide/main/images/kan/landscape/184e38e122683ba5a34b1e1793f3bc28.jpg" />
  </programme>
  <programme start="20260325232300 +0000" stop="20260325234900 +0000" channel="Kan 11">
    <title lang="he">מועדון הסטנד אפ</title>
    <sub-title lang="he">עונה 2 - 1</sub-title>
    <desc lang="he">עונה 2 לתכנית הבידור שבה קטעי סטנד אפ קמים לתחייה והופכים למערכונים. הפעם: אסף מור יוסף בורח מהמשטרה, גיתית פישר רוצה להיות כמו הבנות האלה, איתי זבולון נוסע לאשקלון, ועידן אלתרמן מתקלח בקאנטרי.</desc>
    <category lang="en">Series</category>
    <episode-num system="onscreen">S2E1</episode-num>
    <icon src="https://raw.githubusercontent.com/EMPmaster/tv-guide/main/images/kan/landscape/1179f0c175233b23de59bd5ada40998f.jpg" />
  </programme>
  <programme start="20260325234900 +0000" stop="20260326003500 +0000" channel="Kan 11">
    <title lang="he">סבתא בישלה עם תום יער</title>
    <sub-title lang="he">יש מאין</sub-title>
    <desc lang="he">תום יער במסע קולינרי בין דורי. יש מאין: הפעם תום לומדת מסבתא מרים העיראקית ומסבא קין הסיני איך מכינים ארוחה מפוארת מ(כמעט) כלום. היא תתפלל להצלחת הקובה ותגיע למקום בו היא מרגישה הכי בבית–מסעדה סינית.</desc>
    <category lang="en">Series</category>
    <episode-num system="original-air-date">2026-03-25</episode-num>
    <icon src="https://raw.githubusercontent.com/EMPmaster/tv-guide/main/images/kan/landscape/cb8e91ba1988a29164b17d5ad6b25c78.jpg" />
  </programme>
  <programme start="20260326003500 +0000" stop="20260326004000 +0000" channel="Kan 11">
    <title lang="he">מבזק חדשות</title>
    <desc lang="he">מבזק חדשות</desc>
    <category lang="en">News</category>
    <episode-num system="original-air-date">2026-03-26</episode-num>
    <icon src="https://raw.githubusercontent.com/EMPmaster/tv-guide/main/images/kan/landscape/184e38e122683ba5a34b1e1793f3bc28.jpg" />
  </programme>
  <programme start="20260326004000 +0000" stop="20260326011300 +0000" channel="Kan 11">
    <title lang="he">סיפורים מהכורסה</title>
    <sub-title lang="he">הפעם הראשונה שלי</sub-title>
    <desc lang="he">האנשים המצחיקים בישראל מספרים את הסיפור של כולנו. הפעם: מי קיבלה מחזור וסטירה באותו יום? על מי השתין פיל בקרקס? מי זכתה להצהרת אהבה ראשונה שנגמרה בתאונה? ואת מי זכר נשיא המדינה בגלל רק רצף קללות מטורף?</desc>
    <category lang="en">Series</category>
    <episode-num system="original-air-date">2026-03-26</episode-num>
    <icon src="https://raw.githubusercontent.com/EMPmaster/tv-guide/main/images/kan/landscape/d3cc4f56355c558b3a3dc8e5b01a9a3c.jpg" />
  </programme>
  <programme start="20260326011300 +0000" stop="20260326012500 +0000" channel="Kan 11">
    <title lang="he">מבזק חדשות</title>
    <desc lang="he">מבזק חדשות</desc>
    <category lang="en">News</category>
    <episode-num system="original-air-date">2026-03-26</episode-num>
    <icon src="https://raw.githubusercontent.com/EMPmaster/tv-guide/main/images/kan/landscape/184e38e122683ba5a34b1e1793f3bc28.jpg" />
  </programme>
  <programme start="20260326012500 +0000" stop="20260326020000 +0000" channel="Kan 11">
    <title lang="he">שלומי שבן מארח</title>
    <sub-title lang="he">נינט</sub-title>
    <desc lang="he">שלומי שבן מארח בהיכל התרבות את נינט טייב. נינט ו&quot;באבי&quot; (ככה נינט מכנה את שלומי) בשיחה נונשלנטית וכנה על המוזיקה שלה ועל הדרמות המפוארות בחייה, וגם על זה שאין אצלה הפרדה בין המוסיקה והחיים.</desc>
    <category lang="en">Series</category>
    <episode-num system="original-air-date">2026-03-26</episode-num>
    <icon src="https://raw.githubusercontent.com/EMPmaster/tv-guide/main/images/kan/landscape/656d06f77b98393afc1f2bcb948393cc.jpg" />
  </programme>
  <programme start="20260326020000 +0000" stop="20260326020500 +0000" channel="Kan 11">
    <title lang="he">מבזק חדשות</title>
    <desc lang="he">מבזק חדשות</desc>
    <category lang="en">News</category>
    <episode-num system="original-air-date">2026-03-26</episode-num>
    <icon src="https://raw.githubusercontent.com/EMPmaster/tv-guide/main/images/kan/landscape/184e38e122683ba5a34b1e1793f3bc28.jpg" />
  </programme>
  <programme start="20260326020500 +0000" stop="20260326023900 +0000" channel="Kan 11">
    <title lang="he">אומרים שהיה פה</title>
    <sub-title lang="he">9</sub-title>
    <desc lang="he">מדינת ישראל מציינת עשור וגם את המאבק העדתי הראשון. איזה ברווז הצליח להלחיץ עשרות אלפי אזרחים? מי ניצל את החגיגות כדי לפרוץ לבתים? וגם: מה גרם לבן גוריון לקטוע את מהדורת החדשות ברדיו?</desc>
    <category lang="en">Series</category>
    <episode-num system="onscreen">S1958E9</episode-num>
    <icon src="https://raw.githubusercontent.com/EMPmaster/tv-guide/main/images/kan/landscape/5f4ded6352ee91b840ba8a7370259a12.jpg" />
  </programme>
  <programme start="20260326023900 +0000" stop="20260326031000 +0000" channel="Kan 11">
    <title lang="he">הבלתי חשובים</title>
    <sub-title lang="he">דני קיי</sub-title>
    <desc lang="he">סדרה היסטורית על אירועים שבמבט ראשון נראים בלתי חשובים, אך ממרחק השנים מספרים סיפור גדול יותר על כולנו. והפעם: סיפור של כוכב קולנוע ענק שהתאהב בישראל ובילדיה. אז מי היה דני קיי? ואיך ציפי שביט קשורה לזה?</desc>
    <category lang="en">Series</category>
    <episode-num system="original-air-date">2026-03-26</episode-num>
    <icon src="https://raw.githubusercontent.com/EMPmaster/tv-guide/main/images/kan/landscape/061447c05e36d16c82ceed7bd90bcdf2.jpg" />
  </programme>
  <programme start="20260326031000 +0000" stop="20260326031500 +0000" channel="Kan 11">
    <title lang="he">מבזק חדשות</title>
    <desc lang="he">מבזק חדשות</desc>
    <category lang="en">News</category>
    <episode-num system="original-air-date">2026-03-26</episode-num>
    <icon src="https://raw.githubusercontent.com/EMPmaster/tv-guide/main/images/kan/landscape/184e38e122683ba5a34b1e1793f3bc28.jpg" />
  </programme>
  <programme start="20260326031500 +0000" stop="20260326034500 +0000" channel="Kan 11">
    <title lang="he">שיר אחד</title>
    <sub-title lang="he">זאת שמעל לכל המצופה</sub-title>
    <desc lang="he">סיפורו של השיר &quot;זאת שמעל לכל המצופה&quot; - שיר על אהבה לאישה בלתי מושגת שנכתב לשלישיית הגשש החיוור, והתגלגל חזרה לדני סנדרסון, האיש שיצר אותו מתוך חייו שלו, על אף שכבר זכה בליבה של זאת שמעל לכל המצופה.</desc>
    <category lang="en">Series</category>
    <episode-num system="original-air-date">2026-03-26</episode-num>
    <icon src="https://raw.githubusercontent.com/EMPmaster/tv-guide/main/images/kan/landscape/143619d6989cb01b29e0c06005cb0f7e.jpg" />
  </programme>
  <programme start="20260326034500 +0000" stop="20260326040000 +0000" channel="Kan 11">
    <title lang="he">מהצד השני עם גיא זהר</title>
    <desc lang="he">בימים של שטף בלתי פוסק של מסרים ואינפורמציה, יש מי שמנסה לעשות סדר. גיא זהר בטור יומי, חושף את הפער שבין המציאות לבין הדרך בה היא משתקפת בתקשורת, ואת המנגנונים שמעצבים לנו אותה.</desc>
    <category lang="en">Series</category>
    <episode-num system="original-air-date">2026-03-26</episode-num>
    <icon src="https://raw.githubusercontent.com/EMPmaster/tv-guide/main/images/kan/landscape/7fc074205e6ec57ae2af029c902e3c2b.jpg" />
  </programme>
  <programme start="20260326040000 +0000" stop="20260326060000 +0000" channel="Kan 11">
    <title lang="he">הבוקר הזה עם אילאיל שחר</title>
    <desc lang="he">שידור חי של יומן הבוקר מ&quot;כאן חדשות ברשת ב&quot;.</desc>
    <category lang="en">News</category>
    <episode-num system="original-air-date">2026-03-26</episode-num>
    <icon src="https://raw.githubusercontent.com/EMPmaster/tv-guide/main/images/kan/landscape/99b149eb4ccc2013d1076f650b0e5b05.jpg" />
  </programme>
  <programme start="20260326060000 +0000" stop="20260326080000 +0000" channel="Kan 11">
    <title lang="he">עקיבא נוביק ורינה מצליח</title>
    <desc lang="he">שידור חי של תוכנית הרדיו של &quot;כאן חדשות ברשת ב&quot; בהגשת עקיבא נוביק ורינה מצליח.</desc>
    <category lang="en">Series</category>
    <episode-num system="original-air-date">2026-03-26</episode-num>
    <icon src="https://raw.githubusercontent.com/EMPmaster/tv-guide/main/images/kan/landscape/b05ddda48a17c8ab3296a1070a0952f2.jpg" />
  </programme>
  <programme start="20260326080000 +0000" stop="20260326100000 +0000" channel="Kan 11">
    <title lang="he">רוני קובן ועמרי אסנהיים</title>
    <desc lang="he">תכנית אקטואליה שבועית. רוני קובן ועמרי אסנהיים מסכמים את השבוע.</desc>
    <category lang="en">Series</category>
    <episode-num system="original-air-date">2026-03-26</episode-num>
    <icon src="https://raw.githubusercontent.com/EMPmaster/tv-guide/main/images/kan/landscape/490d84901a3fef9aa208f28ebd7fc661.jpg" />
  </programme>
  <programme start="20260326100000 +0000" stop="20260326120000 +0000" channel="Kan 11">
    <title lang="he">משדר מיוחד-יפעת גליק ותמר אלמוג</title>
    <desc lang="he">משדר חדשות מיוחד עם יפעת גליק ותמר אלמוג.</desc>
    <category lang="en">News</category>
    <episode-num system="original-air-date">2026-03-26</episode-num>
    <icon src="https://raw.githubusercontent.com/EMPmaster/tv-guide/main/images/kan/landscape/f99e66797e4dd9ed3781a31790152397.jpg" />
  </programme>
  <programme start="20260326120000 +0000" stop="20260326140000 +0000" channel="Kan 11">
    <title lang="he">משדר מיוחד עם יונתן אוחיון</title>
    <desc lang="he">משדר חדשות מיוחד עם יונתן אוחיון.</desc>
    <category lang="en">News</category>
    <episode-num system="original-air-date">2026-03-26</episode-num>
    <icon src="https://raw.githubusercontent.com/EMPmaster/tv-guide/main/images/kan/landscape/f99e66797e4dd9ed3781a31790152397.jpg" />
  </programme>
  <programme start="20260326140000 +0000" stop="20260326160000 +0000" channel="Kan 11">
    <title lang="he">משדר מיוחד עם מאיה ראכלין</title>
    <desc lang="he">משדר חדשות מיוחד עם מאיה ראכלין.</desc>
    <category lang="en">News</category>
    <episode-num system="original-air-date">2026-03-26</episode-num>
    <icon src="https://raw.githubusercontent.com/EMPmaster/tv-guide/main/images/kan/landscape/f99e66797e4dd9ed3781a31790152397.jpg" />
  </programme>
  <programme start="20260326160000 +0000" stop="20260326175000 +0000" channel="Kan 11">
    <title lang="he">משדר מיוחד עם איילה חסון</title>
    <desc lang="he">משדר חדשות מיוחד עם איילה חסון.</desc>
    <category lang="en">News</category>
    <episode-num system="original-air-date">2026-03-26</episode-num>
    <icon src="https://raw.githubusercontent.com/EMPmaster/tv-guide/main/images/kan/landscape/f99e66797e4dd9ed3781a31790152397.jpg" />
  </programme>
  <programme start="20260326175000 +0000" stop="20260326193000 +0000" channel="Kan 11">
    <title lang="he">מהדורת כאן חדשות עם טל ברמן</title>
    <desc lang="he">מהדורת החדשות המרכזית של כאן 11 עם נבחרת הכתבים והפרשנים של כאן חדשות. הפרסומים הראשונים, הכותרות החמות וכל הפרשנויות לצד כתבות מגזין ופינות קבועות.</desc>
    <category lang="en">News</category>
    <episode-num system="original-air-date">2026-03-26</episode-num>
    <icon src="https://raw.githubusercontent.com/EMPmaster/tv-guide/main/images/kan/landscape/7a04ba8f5e74f1d0dbcb0373d86cf287.jpg" />
  </programme>
  <programme start="20260326193000 +0000" stop="20260326200500 +0000" channel="Kan 11">
    <title lang="he">מה שתגידו</title>
    <sub-title lang="he">עונה חדשה</sub-title>
    <desc lang="he">הזוגות עם הפה הכי גדול בטלוויזיה חוזרים בעונה חדשה כדי לסכם את השבוע שחלף, בלי פילטרים.</desc>
    <category lang="en">Series</category>
    <episode-num system="original-air-date">2026-03-26</episode-num>
    <icon src="https://raw.githubusercontent.com/EMPmaster/tv-guide/main/images/kan/landscape/0606e5a942200ad236ab413a30744f0a.jpg" />
  </programme>
  <programme start="20260326200500 +0000" stop="20260326204000 +0000" channel="Kan 11">
    <title lang="he">אתה חייב לקרוא את זה!</title>
    <sub-title lang="he">עונה חדשה</sub-title>
    <desc lang="he">קומיקאים ואנשי ספר נאבקים על המלצת הקריאה המושלמת. בלי רחמים. והפעם גיתית פישר, שיר ראובן, ג&apos;רמי פוגל, אמה אלפי, רבקה מיכאלי ויובל מנדלסון ממליצים לאחות המלווה אנשים להמתת חסד בשוויץ ולנערה &quot;בוקטוקרית&quot;.</desc>
    <category lang="en">Series</category>
    <episode-num system="original-air-date">2026-03-26</episode-num>
    <icon src="https://raw.githubusercontent.com/EMPmaster/tv-guide/main/images/kan/landscape/b511f8334036c3a128fec79bfd05c087.jpg" />
  </programme>
  <programme start="20260326204000 +0000" stop="20260326220000 +0000" channel="Kan 11">
    <title lang="he">חדשות הלילה עם ליאל קייזר</title>
    <desc lang="he">רגע לפני שהיום נגמר, חדשות הלילה תסכם עבורכם את כל הדברים החשובים והמעניינים שקרו היום – מזווית קצת אחרת.</desc>
    <category lang="en">News</category>
    <episode-num system="original-air-date">2026-03-26</episode-num>
    <icon src="https://raw.githubusercontent.com/EMPmaster/tv-guide/main/images/kan/landscape/4cb0dc1cda860f43b6be7da0eb09fcef.jpg" />
  </programme>
  <programme start="20260326220000 +0000" stop="20260326221500 +0000" channel="Kan 11">
    <title lang="he">מהצד השני עם גיא זהר</title>
    <desc lang="he">בימים של שטף בלתי פוסק של מסרים ואינפורמציה, יש מי שמנסה לעשות סדר. גיא זהר בטור יומי, חושף את הפער שבין המציאות לבין הדרך בה היא משתקפת בתקשורת, ואת המנגנונים שמעצבים לנו אותה.</desc>
    <category lang="en">Series</category>
    <episode-num system="original-air-date">2026-03-26</episode-num>
    <icon src="https://raw.githubusercontent.com/EMPmaster/tv-guide/main/images/kan/landscape/7fc074205e6ec57ae2af029c902e3c2b.jpg" />
  </programme>
  <programme start="20260326221500 +0000" stop="20260326230000 +0000" channel="Kan 11">
    <title lang="he">הסוכנות</title>
    <sub-title lang="he">פרק 1-ראשים יעופו</sub-title>
    <desc lang="he">עונה חדשה לסדרת המתח הצרפתית. פרק 1: מלוטרו בורח למוסקבה כדי לחמוק ממנהל הביטחון ומסוכנות הביון האמריקנית. מנהל האבטחה החדש מורה על ביקורת מקיפה של הסוכנות ושל המנהלת החדשה מארי-ז&apos;אן.</desc>
    <category lang="en">Series</category>
    <episode-num system="onscreen">S4E1</episode-num>
    <icon src="https://raw.githubusercontent.com/EMPmaster/tv-guide/main/images/kan/landscape/69e984529180222f94f358eea9b3533b.jpg" />
  </programme>
  <programme start="20260326230000 +0000" stop="20260326231423 +0000" channel="Kan 11">
    <title lang="he">מבזק חדשות</title>
    <desc lang="he">מבזק חדשות</desc>
    <category lang="en">News</category>
    <episode-num system="original-air-date">2026-03-26</episode-num>
    <icon src="https://raw.githubusercontent.com/EMPmaster/tv-guide/main/images/kan/landscape/184e38e122683ba5a34b1e1793f3bc28.jpg" />
  </programme>
  <programme start="20260326231423 +0000" stop="20260326234050 +0000" channel="Kan 11">
    <title lang="he">מועדון הסטנד אפ</title>
    <sub-title lang="he">עונה 2 -2</sub-title>
    <desc lang="he">עונה 2 לתכנית הבידור. הפעם: תום יער מזמינה על בעלה גרוזינים עם אלות, אבי נוסבאום מצא טריק לא לשלם בחניון, מתן פרץ אוהב בנות שמעשנות וויד, אורנה בנאי רבה עם חברה שלה ומני עוזרי מקבל ברכה ריחנית במיוחד.</desc>
    <category lang="en">Series</category>
    <episode-num system="onscreen">S2E2</episode-num>
    <icon src="https://raw.githubusercontent.com/EMPmaster/tv-guide/main/images/kan/landscape/1179f0c175233b23de59bd5ada40998f.jpg" />
  </programme>
  <programme start="20260326234050 +0000" stop="20260326244050 +0000" channel="Kan 11">
    <title lang="he">סבתא בישלה עם תום יער</title>
    <sub-title lang="he">שמחות</sub-title>
    <desc lang="he">תום יער במפגש קולינרי בין-דורי עם סבתא שולה התורכיה וסבתא וסבא מריה ואדי האוקראינים, שאוהבים לשמוח. תום תלמד לתפור דג ולסרוג גרביים, תחגוג יום הולדת מיוחד לנונה צ&apos;יקה וגם את יום הניצחון על הנאצים.</desc>
    <category lang="en">Series</category>
    <episode-num system="original-air-date">2026-03-26</episode-num>
    <icon src="https://raw.githubusercontent.com/EMPmaster/tv-guide/main/images/kan/landscape/cb8e91ba1988a29164b17d5ad6b25c78.jpg" />
  </programme>
</tv>